{
  "tracks": {
    "POP OUT": {
      "play_count": 27,
      "last_played": "2026-01-23T12:02:33.507282"
    },
    "SOUTH ATLANTA BABY": {
      "play_count": 2,
      "last_played": "2026-01-23T11:55:42.237627"
    },
    "CRUSH": {
      "play_count": 21,
      "last_played": "2026-01-23T12:02:35.538075"
    },
    "BACKD00R": {
      "play_count": 7,
      "last_played": "2026-01-23T12:05:07.252961"
    },
    "RATHER LIE": {
      "play_count": 6,
      "last_played": "2026-01-23T12:03:18.526366"
    },
    "TWIN TRIM": {
      "play_count": 17,
      "last_played": "2026-01-23T11:38:19.852536"
    },
    "K POP": {
      "play_count": 9,
      "last_played": "2026-01-23T12:02:44.193254"
    },
    "Track 16": {
      "play_count": 25,
      "last_played": "2026-01-23T11:23:09.426767"
    },
    "EVIL J0RDAN": {
      "play_count": 6,
      "last_played": "2026-01-23T12:02:47.716447"
    },
    "MOJO JOJO": {
      "play_count": 5,
      "last_played": "2026-01-23T12:02:49.121035"
    },
    "PHILLY": {
      "play_count": 5,
      "last_played": "2026-01-23T12:02:51.527405"
    },
    "RADAR": {
      "play_count": 6,
      "last_played": "2026-01-23T12:03:17.070290"
    },
    "FINE SHIT": {
      "play_count": 5,
      "last_played": "2026-01-23T12:03:20.304624"
    },
    "TOXIC": {
      "play_count": 5,
      "last_played": "2026-01-23T12:08:17.593448"
    },
    "MUNYUN": {
      "play_count": 4,
      "last_played": "2026-01-21T21:02:05.424144"
    },
    "CRANK": {
      "play_count": 4,
      "last_played": "2026-01-21T21:02:06.111365"
    },
    "CHARGE DEM HOES A FEE": {
      "play_count": 4,
      "last_played": "2026-01-21T21:02:07.081401"
    },
    "GOOD CREDIT": {
      "play_count": 4,
      "last_played": "2026-01-21T21:02:07.810433"
    },
    "I SEEEEEE YOU BABY BOI": {
      "play_count": 3,
      "last_played": "2026-01-21T21:02:08.275124"
    },
    "WAKE UP F1LTHY": {
      "play_count": 2,
      "last_played": "2026-01-23T11:36:25.100564"
    },
    "JUMPIN": {
      "play_count": 1,
      "last_played": "2026-01-21T21:07:36.664059"
    },
    "TRIM": {
      "play_count": 1,
      "last_played": "2026-01-21T21:07:41.370928"
    },
    "COCAINE NOSE": {
      "play_count": 1,
      "last_played": "2026-01-21T21:07:43.175861"
    },
    "Rockstar Made": {
      "play_count": 4,
      "last_played": "2026-01-21T21:56:54.596113"
    },
    "Go2DaMoon": {
      "play_count": 3,
      "last_played": "2026-01-21T21:57:32.450706"
    },
    "Stop Breathing": {
      "play_count": 3,
      "last_played": "2026-01-21T21:57:33.160075"
    },
    "Beno!": {
      "play_count": 2,
      "last_played": "2026-01-21T21:57:33.874530"
    },
    "JumpOutTheHouse": {
      "play_count": 1,
      "last_played": "2026-01-21T21:57:34.577836"
    },
    "M3tamorphosis": {
      "play_count": 1,
      "last_played": "2026-01-21T21:57:35.439514"
    },
    "Slay3r": {
      "play_count": 1,
      "last_played": "2026-01-21T21:57:37.251504"
    },
    "No Sl33p": {
      "play_count": 1,
      "last_played": "2026-01-21T22:00:21.883120"
    },
    "New Tank": {
      "play_count": 1,
      "last_played": "2026-01-21T22:01:05.425816"
    },
    "Teen X": {
      "play_count": 1,
      "last_played": "2026-01-21T22:01:06.675237"
    },
    "Meh": {
      "play_count": 1,
      "last_played": "2026-01-21T22:01:07.805117"
    },
    "Vamp Anthem": {
      "play_count": 1,
      "last_played": "2026-01-21T22:01:09.035233"
    },
    "New N3on": {
      "play_count": 1,
      "last_played": "2026-01-21T22:01:10.772883"
    },
    "Control": {
      "play_count": 1,
      "last_played": "2026-01-21T22:01:12.656761"
    },
    "WALK": {
      "play_count": 5,
      "last_played": "2026-01-23T11:36:29.561611"
    },
    "WE NEED ALL DA VIBES": {
      "play_count": 1,
      "last_played": "2026-01-23T11:32:52.911866"
    },
    "OVERLY": {
      "play_count": 6,
      "last_played": "2026-01-23T11:49:52.815467"
    }
  }
}